{
  "location": {
    "name": "Bengaluru",
    "region": "Karnataka",
    "country": "India",
    "lat": 12.9833,
    "lon": 77.5833,
    "tz_id": "Asia/Kolkata",
    "localtime_epoch": 1760347368,
    "localtime": "2025-10-13 14:52"
  },
  "current": {
    "last_updated_epoch": 1760346900,
    "last_updated": "2025-10-13 14:45",
    "temp_c": 28.2,
    "temp_f": 82.8,
    "is_day": 1,
    "condition": {
      "text": "Patchy rain nearby",
      "icon": "//cdn.weatherapi.com/weather/64x64/day/176.png",
      "code": 1063
    },
    "wind_mph": 6.7,
    "wind_kph": 10.8,
    "wind_degree": 27,
    "wind_dir": "NNE",
    "pressure_mb": 1013.0,
    "pressure_in": 29.91,
    "precip_mm": 0.5,
    "precip_in": 0.02,
    "humidity": 45,
    "cloud": 25,
    "feelslike_c": 30.4,
    "feelslike_f": 86.8,
    "windchill_c": 26.2,
    "windchill_f": 79.2,
    "heatindex_c": 27.6,
    "heatindex_f": 81.8,
    "dewpoint_c": 18.8,
    "dewpoint_f": 65.8,
    "vis_km": 6.0,
    "vis_miles": 3.0,
    "uv": 4.9,
    "gust_mph": 10.2,
    "gust_kph": 16.4,
    "air_quality": {
      "co": 946.85,
      "no2": 18.25,
      "o3": 118.0,
      "so2": 20.15,
      "pm2_5": 39.05,
      "pm10": 42.05,
      "us-epa-index": 2,
      "gb-defra-index": 4
    }
  },
  "forecast": {
    "forecastday": [
      {
        "date": "2025-10-13",
        "date_epoch": 1760313600,
        "day": {
          "maxtemp_c": 27.1,
          "maxtemp_f": 80.8,
          "mintemp_c": 20.4,
          "mintemp_f": 68.6,
          "avgtemp_c": 22.9,
          "avgtemp_f": 73.3,
          "maxwind_mph": 7.8,
          "maxwind_kph": 12.6,
          "totalprecip_mm": 6.37,
          "totalprecip_in": 0.25,
          "totalsnow_cm": 0.0,
          "avgvis_km": 9.8,
          "avgvis_miles": 6.0,
          "avghumidity": 76,
          "daily_will_it_rain": 1,
          "daily_chance_of_rain": 96,
          "daily_will_it_snow": 0,
          "daily_chance_of_snow": 0,
          "condition": {
            "text": "Moderate rain",
            "icon": "//cdn.weatherapi.com/weather/64x64/day/302.png",
            "code": 1189
          },
          "uv": 2.1
        },
        "astro": {
          "moonrise": "11:57 PM",
          "moonset": "12:22 PM",
          "sunrise": "06:10 AM",
          "sunset": "06:02 PM",
          "moon_phase": "Last Quarter",
          "moon_illumination": 58,
          "is_moon_up": 1,
          "is_sun_up": 0
        },
        "hour": [
          {
            "time_epoch": 1760293800,
            "time": "2025-10-13 00:00",
            "temp_c": 21.5,
            "temp_f": 70.7,
            "is_day": 0,
            "condition": {
              "text": "Patchy rain nearby",
              "icon": "//cdn.weatherapi.com/weather/64x64/night/176.png",
              "code": 1063
            },
            "wind_mph": 3.8,
            "wind_kph": 6.1,
            "wind_degree": 77,
            "wind_dir": "ENE",
            "pressure_mb": 1011.0,
            "pressure_in": 29.86,
            "precip_mm": 0.14,
            "precip_in": 0.01,
            "snow_cm": 0.0,
            "humidity": 74,
            "cloud": 86,
            "feelslike_c": 21.5,
            "feelslike_f": 70.7,
            "windchill_c": 21.5,
            "windchill_f": 70.7,
            "heatindex_c": 24.4,
            "heatindex_f": 76.0,
            "dewpoint_c": 16.6,
            "dewpoint_f": 61.9,
            "will_it_rain": 1,
            "chance_of_rain": 100,
            "will_it_snow": 0,
            "chance_of_snow": 0,
            "vis_km": 10.0,
            "vis_miles": 6.0,
            "gust_mph": 7.0,
            "gust_kph": 11.3,
            "uv": 0
          },
          {
            "time_epoch": 1760297400,
            "time": "2025-10-13 01:00",
            "temp_c": 21.3,
            "temp_f": 70.4,
            "is_day": 0,
            "condition": {
              "text": "Patchy rain nearby",
              "icon": "//cdn.weatherapi.com/weather/64x64/night/176.png",
              "code": 1063
            },
            "wind_mph": 3.4,
            "wind_kph": 5.4,
            "wind_degree": 67,
            "wind_dir": "ENE",
            "pressure_mb": 1010.0,
            "pressure_in": 29.84,
            "precip_mm": 0.03,
            "precip_in": 0.0,
            "snow_cm": 0.0,
            "humidity": 75,
            "cloud": 87,
            "feelslike_c": 21.3,
            "feelslike_f": 70.4,
            "windchill_c": 21.3,
            "windchill_f": 70.4,
            "heatindex_c": 24.4,
            "heatindex_f": 75.9,
            "dewpoint_c": 16.8,
            "dewpoint_f": 62.2,
            "will_it_rain": 1,
            "chance_of_rain": 84,
            "will_it_snow": 0,
            "chance_of_snow": 0,
            "vis_km": 10.0,
            "vis_miles": 6.0,
            "gust_mph": 6.2,
            "gust_kph": 9.9,
            "uv": 0
          },
          {
            "time_epoch": 1760301000,
            "time": "2025-10-13 02:00",
            "temp_c": 20.8,
            "temp_f": 69.5,
            "is_day": 0,
            "condition": {
              "text": "Clear ",
              "icon": "//cdn.weatherapi.com/weather/64x64/night/113.png",
              "code": 1000
            },
            "wind_mph": 3.8,
            "wind_kph": 6.1,
            "wind_degree": 50,
            "wind_dir": "NE",
            "pressure_mb": 1010.0,
            "pressure_in": 29.82,
            "precip_mm": 0.0,
            "precip_in": 0.0,
            "snow_cm": 0.0,
            "humidity": 73,
            "cloud": 24,
            "feelslike_c": 20.8,
            "feelslike_f": 69.5,
            "windchill_c": 20.8,
            "windchill_f": 69.5,
            "heatindex_c": 20.8,
            "heatindex_f": 69.5,
            "dewpoint_c": 15.9,
            "dewpoint_f": 60.7,
            "will_it_rain": 0,
            "chance_of_rain": 0,
            "will_it_snow": 0,
            "chance_of_snow": 0,
            "vis_km": 10.0,
            "vis_miles": 6.0,
            "gust_mph": 7.1,
            "gust_kph": 11.4,
            "uv": 0
          },
          {
            "time_epoch": 1760304600,
            "time": "2025-10-13 03:00",
            "temp_c": 20.6,
            "temp_f": 69.0,
            "is_day": 0,
            "condition": {
              "text": "Clear ",
              "icon": "//cdn.weatherapi.com/weather/64x64/night/113.png",
              "code": 1000
            },
            "wind_mph": 4.7,
            "wind_kph": 7.6,
            "wind_degree": 40,
            "wind_dir": "NE",
            "pressure_mb": 1010.0,
            "pressure_in": 29.82,
            "precip_mm": 0.0,
            "precip_in": 0.0,
            "snow_cm": 0.0,
            "humidity": 76,
            "cloud": 21,
            "feelslike_c": 20.6,
            "feelslike_f": 69.0,
            "windchill_c": 20.6,
            "windchill_f": 69.0,
            "heatindex_c": 20.6,
            "heatindex_f": 69.0,
            "dewpoint_c": 16.2,
            "dewpoint_f": 61.2,
            "will_it_rain": 0,
            "chance_of_rain": 0,
            "will_it_snow": 0,
            "chance_of_snow": 0,
            "vis_km": 10.0,
            "vis_miles": 6.0,
            "gust_mph": 8.8,
            "gust_kph": 14.2,
            "uv": 0
          },
          {
            "time_epoch": 1760308200,
            "time": "2025-10-13 04:00",
            "temp_c": 20.4,
            "temp_f": 68.7,
            "is_day": 0,
            "condition": {
              "text": "Partly Cloudy ",
              "icon": "//cdn.weatherapi.com/weather/64x64/night/116.png",
              "code": 1003
            },
            "wind_mph": 2.7,
            "wind_kph": 4.3,
            "wind_degree": 55,
            "wind_dir": "NE",
            "pressure_mb": 1010.0,
            "pressure_in": 29.83,
            "precip_mm": 0.0,
            "precip_in": 0.0,
            "snow_cm": 0.0,
            "humidity": 79,
            "cloud": 28,
            "feelslike_c": 20.4,
            "feelslike_f": 68.7,
            "windchill_c": 20.4,
            "windchill_f": 68.7,
            "heatindex_c": 20.4,
            "heatindex_f": 68.7,
            "dewpoint_c": 16.7,
            "dewpoint_f": 62.1,
            "will_it_rain": 0,
            "chance_of_rain": 0,
            "will_it_snow": 0,
            "chance_of_snow": 0,
            "vis_km": 10.0,
            "vis_miles": 6.0,
            "gust_mph": 5.0,
            "gust_kph": 8.0,
            "uv": 0
          },
          {
            "time_epoch": 1760311800,
            "time": "2025-10-13 05:00",
            "temp_c": 20.4,
            "temp_f": 68.6,
            "is_day": 0,
            "condition": {
              "text": "Partly Cloudy ",
              "icon": "//cdn.weatherapi.com/weather/64x64/night/116.png",
              "code": 1003
            },
            "wind_mph": 2.7,
            "wind_kph": 4.3,
            "wind_degree": 57,
            "wind_dir": "ENE",
            "pressure_mb": 1011.0,
            "pressure_in": 29.85,
            "precip_mm": 0.0,
            "precip_in": 0.0,
            "snow_cm": 0.0,
            "humidity": 82,
            "cloud": 34,
            "feelslike_c": 20.4,
            "feelslike_f": 68.6,
            "windchill_c": 20.4,
            "windchill_f": 68.6,
            "heatindex_c": 20.4,
            "heatindex_f": 68.6,
            "dewpoint_c": 17.1,
            "dewpoint_f": 62.8,
            "will_it_rain": 0,
            "chance_of_rain": 0,
            "will_it_snow": 0,
            "chance_of_snow": 0,
            "vis_km": 10.0,
            "vis_miles": 6.0,
            "gust_mph": 4.9,
            "gust_kph": 8.0,
            "uv": 0
          },
          {
            "time_epoch": 1760315400,
            "time": "2025-10-13 06:00",
            "temp_c": 20.5,
            "temp_f": 68.9,
            "is_day": 1,
            "condition": {
              "text": "Partly Cloudy ",
              "icon": "//cdn.weatherapi.com/weather/64x64/day/116.png",
              "code": 1003
            },
            "wind_mph": 3.1,
            "wind_kph": 5.0,
            "wind_degree": 48,
            "wind_dir": "NE",
            "pressure_mb": 1012.0,
            "pressure_in": 29.87,
            "precip_mm": 0.0,
            "precip_in": 0.0,
            "snow_cm": 0.0,
            "humidity": 84,
            "cloud": 36,
            "feelslike_c": 20.5,
            "feelslike_f": 68.9,
            "windchill_c": 20.5,
            "windchill_f": 68.9,
            "heatindex_c": 20.5,
            "heatindex_f": 68.9,
            "dewpoint_c": 17.7,
            "dewpoint_f": 63.9,
            "will_it_rain": 0,
            "chance_of_rain": 0,
            "will_it_snow": 0,
            "chance_of_snow": 0,
            "vis_km": 10.0,
            "vis_miles": 6.0,
            "gust_mph": 5.6,
            "gust_kph": 9.0,
            "uv": 0.0
          },
          {
            "time_epoch": 1760319000,
            "time": "2025-10-13 07:00",
            "temp_c": 22.0,
            "temp_f": 71.6,
            "is_day": 1,
            "condition": {
              "text": "Patchy rain nearby",
              "icon": "//cdn.weatherapi.com/weather/64x64/day/176.png",
              "code": 1063
            },
            "wind_mph": 3.8,
            "wind_kph": 6.1,
            "wind_degree": 35,
            "wind_dir": "NE",
            "pressure_mb": 1012.0,
            "pressure_in": 29.89,
            "precip_mm": 0.01,
            "precip_in": 0.0,
            "snow_cm": 0.0,
            "humidity": 80,
            "cloud": 87,
            "feelslike_c": 24.5,
            "feelslike_f": 76.1,
            "windchill_c": 22.0,
            "windchill_f": 71.6,
            "heatindex_c": 24.5,
            "heatindex_f": 76.1,
            "dewpoint_c": 18.3,
            "dewpoint_f": 65.0,
            "will_it_rain": 0,
            "chance_of_rain": 65,
            "will_it_snow": 0,
            "chance_of_snow": 0,
            "vis_km": 10.0,
            "vis_miles": 6.0,
            "gust_mph": 5.3,
            "gust_kph": 8.5,
            "uv": 0.5
          },
          {
            "time_epoch": 1760322600,
            "time": "2025-10-13 08:00",
            "temp_c": 23.4,
            "temp_f": 74.2,
            "is_day": 1,
            "condition": {
              "text": "Patchy rain nearby",
              "icon": "//cdn.weatherapi.com/weather/64x64/day/176.png",
              "code": 1063
            },
            "wind_mph": 4.9,
            "wind_kph": 7.9,
            "wind_degree": 24,
            "wind_dir": "NNE",
            "pressure_mb": 1012.0,
            "pressure_in": 29.89,
            "precip_mm": 0.07,
            "precip_in": 0.0,
            "snow_cm": 0.0,
            "humidity": 73,
            "cloud": 84,
            "feelslike_c": 25.3,
            "feelslike_f": 77.5,
            "windchill_c": 23.4,
            "windchill_f": 74.2,
            "heatindex_c": 25.3,
            "heatindex_f": 77.5,
            "dewpoint_c": 18.4,
            "dewpoint_f": 65.1,
            "will_it_rain": 1,
            "chance_of_rain": 100,
            "will_it_snow": 0,
            "chance_of_snow": 0,
            "vis_km": 10.0,
            "vis_miles": 6.0,
            "gust_mph": 6.1,
            "gust_kph": 9.8,
            "uv": 1.9
          },
          {
            "time_epoch": 1760326200,
            "time": "2025-10-13 09:00",
            "temp_c": 24.9,
            "temp_f": 76.8,
            "is_day": 1,
            "condition": {
              "text": "Patchy rain nearby",
              "icon": "//cdn.weatherapi.com/weather/64x64/day/176.png",
              "code": 1063
            },
            "wind_mph": 6.5,
            "wind_kph": 10.4,
            "wind_degree": 18,
            "wind_dir": "NNE",
            "pressure_mb": 1012.0,
            "pressure_in": 29.89,
            "precip_mm": 0.1,
            "precip_in": 0.0,
            "snow_cm": 0.0,
            "humidity": 67,
            "cloud": 75,
            "feelslike_c": 26.4,
            "feelslike_f": 79.5,
            "windchill_c": 24.9,
            "windchill_f": 76.8,
            "heatindex_c": 26.4,
            "heatindex_f": 79.5,
            "dewpoint_c": 18.4,
            "dewpoint_f": 65.1,
            "will_it_rain": 1,
            "chance_of_rain": 100,
            "will_it_snow": 0,
            "chance_of_snow": 0,
            "vis_km": 10.0,
            "vis_miles": 6.0,
            "gust_mph": 7.5,
            "gust_kph": 12.0,
            "uv": 4.5
          },
          {
            "time_epoch": 1760329800,
            "time": "2025-10-13 10:00",
            "temp_c": 25.9,
            "temp_f": 78.6,
            "is_day": 1,
            "condition": {
              "text": "Light rain shower",
              "icon": "//cdn.weatherapi.com/weather/64x64/day/353.png",
              "code": 1240
            },
            "wind_mph": 7.8,
            "wind_kph": 12.6,
            "wind_degree": 17,
            "wind_dir": "NNE",
            "pressure_mb": 1012.0,
            "pressure_in": 29.87,
            "precip_mm": 0.27,
            "precip_in": 0.01,
            "snow_cm": 0.0,
            "humidity": 63,
            "cloud": 50,
            "feelslike_c": 27.2,
            "feelslike_f": 81.0,
            "windchill_c": 25.9,
            "windchill_f": 78.6,
            "heatindex_c": 27.2,
            "heatindex_f": 81.0,
            "dewpoint_c": 18.4,
            "dewpoint_f": 65.1,
            "will_it_rain": 1,
            "chance_of_rain": 100,
            "will_it_snow": 0,
            "chance_of_snow": 0,
            "vis_km": 10.0,
            "vis_miles": 6.0,
            "gust_mph": 9.1,
            "gust_kph": 14.7,
            "uv": 7.7
          },
          {
            "time_epoch": 1760333400,
            "time": "2025-10-13 11:00",
            "temp_c": 26.7,
            "temp_f": 80.1,
            "is_day": 1,
            "condition": {
              "text": "Patchy rain nearby",
              "icon": "//cdn.weatherapi.com/weather/64x64/day/176.png",
              "code": 1063
            },
            "wind_mph": 7.8,
            "wind_kph": 12.6,
            "wind_degree": 15,
            "wind_dir": "NNE",
            "pressure_mb": 1010.0,
            "pressure_in": 29.83,
            "precip_mm": 0.23,
            "precip_in": 0.01,
            "snow_cm": 0.0,
            "humidity": 60,
            "cloud": 75,
            "feelslike_c": 28.0,
            "feelslike_f": 82.5,
            "windchill_c": 26.7,
            "windchill_f": 80.1,
            "heatindex_c": 28.0,
            "heatindex_f": 82.5,
            "dewpoint_c": 18.4,
            "dewpoint_f": 65.1,
            "will_it_rain": 1,
            "chance_of_rain": 100,
            "will_it_snow": 0,
            "chance_of_snow": 0,
            "vis_km": 9.0,
            "vis_miles": 5.0,
            "gust_mph": 9.4,
            "gust_kph": 15.2,
            "uv": 10.2
          },
          {
            "time_epoch": 1760337000,
            "time": "2025-10-13 12:00",
            "temp_c": 27.1,
            "temp_f": 80.8,
            "is_day": 1,
            "condition": {
              "text": "Patchy light rain",
              "icon": "//cdn.weatherapi.com/weather/64x64/day/293.png",
              "code": 1180
            },
            "wind_mph": 7.6,
            "wind_kph": 12.2,
            "wind_degree": 15,
            "wind_dir": "NNE",
            "pressure_mb": 1009.0,
            "pressure_in": 29.8,
            "precip_mm": 1.14,
            "precip_in": 0.04,
            "snow_cm": 0.0,
            "humidity": 59,
            "cloud": 85,
            "feelslike_c": 28.4,
            "feelslike_f": 83.2,
            "windchill_c": 27.1,
            "windchill_f": 80.8,
            "heatindex_c": 28.4,
            "heatindex_f": 83.2,
            "dewpoint_c": 18.4,
            "dewpoint_f": 65.2,
            "will_it_rain": 1,
            "chance_of_rain": 100,
            "will_it_snow": 0,
            "chance_of_snow": 0,
            "vis_km": 9.0,
            "vis_miles": 5.0,
            "gust_mph": 9.1,
            "gust_kph": 14.7,
            "uv": 10.6
          },
          {
            "time_epoch": 1760340600,
            "time": "2025-10-13 13:00",
            "temp_c": 26.8,
            "temp_f": 80.3,
            "is_day": 1,
            "condition": {
              "text": "Light rain shower",
              "icon": "//cdn.weatherapi.com/weather/64x64/day/353.png",
              "code": 1240
            },
            "wind_mph": 6.5,
            "wind_kph": 10.4,
            "wind_degree": 22,
            "wind_dir": "NNE",
            "pressure_mb": 1008.0,
            "pressure_in": 29.77,
            "precip_mm": 1.26,
            "precip_in": 0.05,
            "snow_cm": 0.0,
            "humidity": 61,
            "cloud": 79,
            "feelslike_c": 28.2,
            "feelslike_f": 82.7,
            "windchill_c": 26.8,
            "windchill_f": 80.3,
            "heatindex_c": 28.2,
            "heatindex_f": 82.7,
            "dewpoint_c": 18.6,
            "dewpoint_f": 65.5,
            "will_it_rain": 1,
            "chance_of_rain": 100,
            "will_it_snow": 0,
            "chance_of_snow": 0,
            "vis_km": 10.0,
            "vis_miles": 6.0,
            "gust_mph": 8.9,
            "gust_kph": 14.3,
            "uv": 6.3
          },
          {
            "time_epoch": 1760344200,
            "time": "2025-10-13 14:00",
            "temp_c": 28.2,
            "temp_f": 82.8,
            "is_day": 1,
            "condition": {
              "text": "Patchy rain nearby",
              "icon": "//cdn.weatherapi.com/weather/64x64/day/176.png",
              "code": 1063
            },
            "wind_mph": 6.7,
            "wind_kph": 10.8,
            "wind_degree": 27,
            "wind_dir": "NNE",
            "pressure_mb": 1013.0,
            "pressure_in": 29.91,
            "precip_mm": 0.5,
            "precip_in": 0.02,
            "snow_cm": 0.0,
            "humidity": 45,
            "cloud": 25,
            "feelslike_c": 27.6,
            "feelslike_f": 81.8,
            "windchill_c": 26.2,
            "windchill_f": 79.2,
            "heatindex_c": 27.6,
            "heatindex_f": 81.8,
            "dewpoint_c": 18.8,
            "dewpoint_f": 65.8,
            "will_it_rain": 1,
            "chance_of_rain": 100,
            "will_it_snow": 0,
            "chance_of_snow": 0,
            "vis_km": 6.0,
            "vis_miles": 3.0,
            "gust_mph": 10.2,
            "gust_kph": 16.4,
            "uv": 4.9
          },
          {
            "time_epoch": 1760347800,
            "time": "2025-10-13 15:00",
            "temp_c": 25.1,
            "temp_f": 77.1,
            "is_day": 1,
            "condition": {
              "text": "Patchy rain nearby",
              "icon": "//cdn.weatherapi.com/weather/64x64/day/176.png",
              "code": 1063
            },
            "wind_mph": 6.7,
            "wind_kph": 10.8,
            "wind_degree": 24,
            "wind_dir": "NNE",
            "pressure_mb": 1008.0,
            "pressure_in": 29.75,
            "precip_mm": 0.71,
            "precip_in": 0.03,
            "snow_cm": 0.0,
            "humidity": 73,
            "cloud": 86,
            "feelslike_c": 26.8,
            "feelslike_f": 80.2,
            "windchill_c": 25.1,
            "windchill_f": 77.1,
            "heatindex_c": 26.8,
            "heatindex_f": 80.2,
            "dewpoint_c": 19.8,
            "dewpoint_f": 67.7,
            "will_it_rain": 1,
            "chance_of_rain": 100,
            "will_it_snow": 0,
            "chance_of_snow": 0,
            "vis_km": 9.0,
            "vis_miles": 5.0,
            "gust_mph": 10.7,
            "gust_kph": 17.2,
            "uv": 2.6
          },
          {
            "time_epoch": 1760351400,
            "time": "2025-10-13 16:00",
            "temp_c": 23.8,
            "temp_f": 74.9,
            "is_day": 1,
            "condition": {
              "text": "Patchy rain nearby",
              "icon": "//cdn.weatherapi.com/weather/64x64/day/176.png",
              "code": 1063
            },
            "wind_mph": 6.5,
            "wind_kph": 10.4,
            "wind_degree": 21,
            "wind_dir": "NNE",
            "pressure_mb": 1008.0,
            "pressure_in": 29.77,
            "precip_mm": 0.75,
            "precip_in": 0.03,
            "snow_cm": 0.0,
            "humidity": 79,
            "cloud": 77,
            "feelslike_c": 25.7,
            "feelslike_f": 78.3,
            "windchill_c": 23.8,
            "windchill_f": 74.9,
            "heatindex_c": 25.7,
            "heatindex_f": 78.3,
            "dewpoint_c": 19.9,
            "dewpoint_f": 67.9,
            "will_it_rain": 1,
            "chance_of_rain": 100,
            "will_it_snow": 0,
            "chance_of_snow": 0,
            "vis_km": 9.0,
            "vis_miles": 5.0,
            "gust_mph": 11.0,
            "gust_kph": 17.7,
            "uv": 0.7
          },
          {
            "time_epoch": 1760355000,
            "time": "2025-10-13 17:00",
            "temp_c": 23.6,
            "temp_f": 74.5,
            "is_day": 1,
            "condition": {
              "text": "Light rain shower",
              "icon": "//cdn.weatherapi.com/weather/64x64/day/353.png",
              "code": 1240
            },
            "wind_mph": 6.3,
            "wind_kph": 10.1,
            "wind_degree": 28,
            "wind_dir": "NNE",
            "pressure_mb": 1009.0,
            "pressure_in": 29.79,
            "precip_mm": 0.77,
            "precip_in": 0.03,
            "snow_cm": 0.0,
            "humidity": 81,
            "cloud": 85,
            "feelslike_c": 25.6,
            "feelslike_f": 78.1,
            "windchill_c": 23.6,
            "windchill_f": 74.5,
            "heatindex_c": 25.6,
            "heatindex_f": 78.1,
            "dewpoint_c": 20.2,
            "dewpoint_f": 68.4,
            "will_it_rain": 1,
            "chance_of_rain": 100,
            "will_it_snow": 0,
            "chance_of_snow": 0,
            "vis_km": 10.0,
            "vis_miles": 6.0,
            "gust_mph": 11.1,
            "gust_kph": 17.9,
            "uv": 0.2
          },
          {
            "time_epoch": 1760358600,
            "time": "2025-10-13 18:00",
            "temp_c": 22.7,
            "temp_f": 72.8,
            "is_day": 0,
            "condition": {
              "text": "Patchy rain nearby",
              "icon": "//cdn.weatherapi.com/weather/64x64/night/176.png",
              "code": 1063
            },
            "wind_mph": 6.9,
            "wind_kph": 11.2,
            "wind_degree": 38,
            "wind_dir": "NE",
            "pressure_mb": 1009.0,
            "pressure_in": 29.8,
            "precip_mm": 0.18,
            "precip_in": 0.01,
            "snow_cm": 0.0,
            "humidity": 84,
            "cloud": 74,
            "feelslike_c": 24.9,
            "feelslike_f": 76.8,
            "windchill_c": 22.7,
            "windchill_f": 72.8,
            "heatindex_c": 24.9,
            "heatindex_f": 76.8,
            "dewpoint_c": 19.9,
            "dewpoint_f": 67.7,
            "will_it_rain": 1,
            "chance_of_rain": 100,
            "will_it_snow": 0,
            "chance_of_snow": 0,
            "vis_km": 9.0,
            "vis_miles": 5.0,
            "gust_mph": 12.1,
            "gust_kph": 19.4,
            "uv": 0
          },
          {
            "time_epoch": 1760362200,
            "time": "2025-10-13 19:00",
            "temp_c": 22.0,
            "temp_f": 71.7,
            "is_day": 0,
            "condition": {
              "text": "Patchy rain nearby",
              "icon": "//cdn.weatherapi.com/weather/64x64/night/176.png",
              "code": 1063
            },
            "wind_mph": 6.7,
            "wind_kph": 10.8,
            "wind_degree": 49,
            "wind_dir": "NE",
            "pressure_mb": 1010.0,
            "pressure_in": 29.83,
            "precip_mm": 0.12,
            "precip_in": 0.0,
            "snow_cm": 0.0,
            "humidity": 86,
            "cloud": 71,
            "feelslike_c": 24.5,
            "feelslike_f": 76.2,
            "windchill_c": 22.0,
            "windchill_f": 71.7,
            "heatindex_c": 24.5,
            "heatindex_f": 76.2,
            "dewpoint_c": 19.6,
            "dewpoint_f": 67.3,
            "will_it_rain": 1,
            "chance_of_rain": 100,
            "will_it_snow": 0,
            "chance_of_snow": 0,
            "vis_km": 10.0,
            "vis_miles": 6.0,
            "gust_mph": 12.1,
            "gust_kph": 19.5,
            "uv": 0
          },
          {
            "time_epoch": 1760365800,
            "time": "2025-10-13 20:00",
            "temp_c": 21.6,
            "temp_f": 71.0,
            "is_day": 0,
            "condition": {
              "text": "Patchy rain nearby",
              "icon": "//cdn.weatherapi.com/weather/64x64/night/176.png",
              "code": 1063
            },
            "wind_mph": 6.3,
            "wind_kph": 10.1,
            "wind_degree": 52,
            "wind_dir": "NE",
            "pressure_mb": 1011.0,
            "pressure_in": 29.86,
            "precip_mm": 0.06,
            "precip_in": 0.0,
            "snow_cm": 0.0,
            "humidity": 87,
            "cloud": 89,
            "feelslike_c": 21.6,
            "feelslike_f": 71.0,
            "windchill_c": 21.6,
            "windchill_f": 71.0,
            "heatindex_c": 24.3,
            "heatindex_f": 75.8,
            "dewpoint_c": 19.5,
            "dewpoint_f": 67.0,
            "will_it_rain": 1,
            "chance_of_rain": 100,
            "will_it_snow": 0,
            "chance_of_snow": 0,
            "vis_km": 10.0,
            "vis_miles": 6.0,
            "gust_mph": 11.5,
            "gust_kph": 18.5,
            "uv": 0
          },
          {
            "time_epoch": 1760369400,
            "time": "2025-10-13 21:00",
            "temp_c": 21.4,
            "temp_f": 70.5,
            "is_day": 0,
            "condition": {
              "text": "Patchy rain nearby",
              "icon": "//cdn.weatherapi.com/weather/64x64/night/176.png",
              "code": 1063
            },
            "wind_mph": 5.8,
            "wind_kph": 9.4,
            "wind_degree": 60,
            "wind_dir": "ENE",
            "pressure_mb": 1012.0,
            "pressure_in": 29.87,
            "precip_mm": 0.04,
            "precip_in": 0.0,
            "snow_cm": 0.0,
            "humidity": 88,
            "cloud": 71,
            "feelslike_c": 21.4,
            "feelslike_f": 70.5,
            "windchill_c": 21.4,
            "windchill_f": 70.5,
            "heatindex_c": 24.3,
            "heatindex_f": 75.7,
            "dewpoint_c": 19.4,
            "dewpoint_f": 66.9,
            "will_it_rain": 1,
            "chance_of_rain": 84,
            "will_it_snow": 0,
            "chance_of_snow": 0,
            "vis_km": 10.0,
            "vis_miles": 6.0,
            "gust_mph": 10.7,
            "gust_kph": 17.2,
            "uv": 0
          },
          {
            "time_epoch": 1760373000,
            "time": "2025-10-13 22:00",
            "temp_c": 21.1,
            "temp_f": 70.0,
            "is_day": 0,
            "condition": {
              "text": "Partly Cloudy ",
              "icon": "//cdn.weatherapi.com/weather/64x64/night/116.png",
              "code": 1003
            },
            "wind_mph": 5.6,
            "wind_kph": 9.0,
            "wind_degree": 73,
            "wind_dir": "ENE",
            "pressure_mb": 1011.0,
            "pressure_in": 29.87,
            "precip_mm": 0.0,
            "precip_in": 0.0,
            "snow_cm": 0.0,
            "humidity": 90,
            "cloud": 55,
            "feelslike_c": 21.1,
            "feelslike_f": 70.0,
            "windchill_c": 21.1,
            "windchill_f": 70.0,
            "heatindex_c": 24.2,
            "heatindex_f": 75.5,
            "dewpoint_c": 19.3,
            "dewpoint_f": 66.7,
            "will_it_rain": 0,
            "chance_of_rain": 0,
            "will_it_snow": 0,
            "chance_of_snow": 0,
            "vis_km": 10.0,
            "vis_miles": 6.0,
            "gust_mph": 10.1,
            "gust_kph": 16.2,
            "uv": 0
          },
          {
            "time_epoch": 1760376600,
            "time": "2025-10-13 23:00",
            "temp_c": 20.8,
            "temp_f": 69.5,
            "is_day": 0,
            "condition": {
              "text": "Partly Cloudy ",
              "icon": "//cdn.weatherapi.com/weather/64x64/night/116.png",
              "code": 1003
            },
            "wind_mph": 5.6,
            "wind_kph": 9.0,
            "wind_degree": 81,
            "wind_dir": "E",
            "pressure_mb": 1011.0,
            "pressure_in": 29.86,
            "precip_mm": 0.0,
            "precip_in": 0.0,
            "snow_cm": 0.0,
            "humidity": 91,
            "cloud": 27,
            "feelslike_c": 20.8,
            "feelslike_f": 69.5,
            "windchill_c": 20.8,
            "windchill_f": 69.5,
            "heatindex_c": 20.8,
            "heatindex_f": 69.5,
            "dewpoint_c": 19.3,
            "dewpoint_f": 66.7,
            "will_it_rain": 0,
            "chance_of_rain": 0,
            "will_it_snow": 0,
            "chance_of_snow": 0,
            "vis_km": 10.0,
            "vis_miles": 6.0,
            "gust_mph": 9.9,
            "gust_kph": 15.9,
            "uv": 0
          }
        ]
      },
      {
        "date": "2025-10-14",
        "date_epoch": 1760400000,
        "day": {
          "maxtemp_c": 26.8,
          "maxtemp_f": 80.3,
          "mintemp_c": 19.8,
          "mintemp_f": 67.6,
          "avgtemp_c": 22.7,
          "avgtemp_f": 72.8,
          "maxwind_mph": 9.6,
          "maxwind_kph": 15.5,
          "totalprecip_mm": 2.98,
          "totalprecip_in": 0.12,
          "totalsnow_cm": 0.0,
          "avgvis_km": 8.9,
          "avgvis_miles": 5.0,
          "avghumidity": 82,
          "daily_will_it_rain": 1,
          "daily_chance_of_rain": 86,
          "daily_will_it_snow": 0,
          "daily_chance_of_snow": 0,
          "condition": {
            "text": "Patchy rain nearby",
            "icon": "//cdn.weatherapi.com/weather/64x64/day/176.png",
            "code": 1063
          },
          "uv": 2.4
        },
        "astro": {
          "moonrise": null,
          "moonset": "01:16 PM",
          "sunrise": "06:10 AM",
          "sunset": "06:01 PM",
          "moon_phase": "Waning Crescent",
          "moon_illumination": 47,
          "is_moon_up": 1,
          "is_sun_up": 0
        },
        "hour": [
          {
            "time_epoch": 1760380200,
            "time": "2025-10-14 00:00",
            "temp_c": 20.6,
            "temp_f": 69.1,
            "is_day": 0,
            "condition": {
              "text": "Partly Cloudy ",
              "icon": "//cdn.weatherapi.com/weather/64x64/night/116.png",
              "code": 1003
            },
            "wind_mph": 5.4,
            "wind_kph": 8.6,
            "wind_degree": 83,
            "wind_dir": "E",
            "pressure_mb": 1010.0,
            "pressure_in": 29.84,
            "precip_mm": 0.0,
            "precip_in": 0.0,
            "snow_cm": 0.0,
            "humidity": 92,
            "cloud": 32,
            "feelslike_c": 20.6,
            "feelslike_f": 69.1,
            "windchill_c": 20.6,
            "windchill_f": 69.1,
            "heatindex_c": 20.6,
            "heatindex_f": 69.1,
            "dewpoint_c": 19.3,
            "dewpoint_f": 66.7,
            "will_it_rain": 0,
            "chance_of_rain": 0,
            "will_it_snow": 0,
            "chance_of_snow": 0,
            "vis_km": 10.0,
            "vis_miles": 6.0,
            "gust_mph": 9.3,
            "gust_kph": 14.9,
            "uv": 0
          },
          {
            "time_epoch": 1760383800,
            "time": "2025-10-14 01:00",
            "temp_c": 20.3,
            "temp_f": 68.6,
            "is_day": 0,
            "condition": {
              "text": "Partly Cloudy ",
              "icon": "//cdn.weatherapi.com/weather/64x64/night/116.png",
              "code": 1003
            },
            "wind_mph": 5.4,
            "wind_kph": 8.6,
            "wind_degree": 86,
            "wind_dir": "E",
            "pressure_mb": 1009.0,
            "pressure_in": 29.81,
            "precip_mm": 0.0,
            "precip_in": 0.0,
            "snow_cm": 0.0,
            "humidity": 93,
            "cloud": 37,
            "feelslike_c": 20.3,
            "feelslike_f": 68.6,
            "windchill_c": 20.3,
            "windchill_f": 68.6,
            "heatindex_c": 20.3,
            "heatindex_f": 68.6,
            "dewpoint_c": 19.2,
            "dewpoint_f": 66.6,
            "will_it_rain": 0,
            "chance_of_rain": 0,
            "will_it_snow": 0,
            "chance_of_snow": 0,
            "vis_km": 10.0,
            "vis_miles": 6.0,
            "gust_mph": 9.3,
            "gust_kph": 15.0,
            "uv": 0
          },
          {
            "time_epoch": 1760387400,
            "time": "2025-10-14 02:00",
            "temp_c": 20.2,
            "temp_f": 68.3,
            "is_day": 0,
            "condition": {
              "text": "Partly Cloudy ",
              "icon": "//cdn.weatherapi.com/weather/64x64/night/116.png",
              "code": 1003
            },
            "wind_mph": 5.1,
            "wind_kph": 8.3,
            "wind_degree": 77,
            "wind_dir": "ENE",
            "pressure_mb": 1009.0,
            "pressure_in": 29.79,
            "precip_mm": 0.0,
            "precip_in": 0.0,
            "snow_cm": 0.0,
            "humidity": 94,
            "cloud": 41,
            "feelslike_c": 20.2,
            "feelslike_f": 68.3,
            "windchill_c": 20.2,
            "windchill_f": 68.3,
            "heatindex_c": 20.2,
            "heatindex_f": 68.3,
            "dewpoint_c": 19.1,
            "dewpoint_f": 66.4,
            "will_it_rain": 0,
            "chance_of_rain": 0,
            "will_it_snow": 0,
            "chance_of_snow": 0,
            "vis_km": 10.0,
            "vis_miles": 6.0,
            "gust_mph": 9.0,
            "gust_kph": 14.5,
            "uv": 0
          },
          {
            "time_epoch": 1760391000,
            "time": "2025-10-14 03:00",
            "temp_c": 20.1,
            "temp_f": 68.1,
            "is_day": 0,
            "condition": {
              "text": "Partly Cloudy ",
              "icon": "//cdn.weatherapi.com/weather/64x64/night/116.png",
              "code": 1003
            },
            "wind_mph": 5.1,
            "wind_kph": 8.3,
            "wind_degree": 70,
            "wind_dir": "ENE",
            "pressure_mb": 1009.0,
            "pressure_in": 29.79,
            "precip_mm": 0.0,
            "precip_in": 0.0,
            "snow_cm": 0.0,
            "humidity": 94,
            "cloud": 39,
            "feelslike_c": 20.1,
            "feelslike_f": 68.1,
            "windchill_c": 20.1,
            "windchill_f": 68.1,
            "heatindex_c": 20.1,
            "heatindex_f": 68.1,
            "dewpoint_c": 19.0,
            "dewpoint_f": 66.2,
            "will_it_rain": 0,
            "chance_of_rain": 0,
            "will_it_snow": 0,
            "chance_of_snow": 0,
            "vis_km": 10.0,
            "vis_miles": 6.0,
            "gust_mph": 9.0,
            "gust_kph": 14.5,
            "uv": 0
          },
          {
            "time_epoch": 1760394600,
            "time": "2025-10-14 04:00",
            "temp_c": 19.9,
            "temp_f": 67.9,
            "is_day": 0,
            "condition": {
              "text": "Mist",
              "icon": "//cdn.weatherapi.com/weather/64x64/night/143.png",
              "code": 1030
            },
            "wind_mph": 5.6,
            "wind_kph": 9.0,
            "wind_degree": 73,
            "wind_dir": "ENE",
            "pressure_mb": 1009.0,
            "pressure_in": 29.79,
            "precip_mm": 0.0,
            "precip_in": 0.0,
            "snow_cm": 0.0,
            "humidity": 94,
            "cloud": 42,
            "feelslike_c": 19.9,
            "feelslike_f": 67.9,
            "windchill_c": 19.9,
            "windchill_f": 67.9,
            "heatindex_c": 19.9,
            "heatindex_f": 67.9,
            "dewpoint_c": 18.9,
            "dewpoint_f": 66.1,
            "will_it_rain": 0,
            "chance_of_rain": 0,
            "will_it_snow": 0,
            "chance_of_snow": 0,
            "vis_km": 2.0,
            "vis_miles": 1.0,
            "gust_mph": 9.7,
            "gust_kph": 15.7,
            "uv": 0
          },
          {
            "time_epoch": 1760398200,
            "time": "2025-10-14 05:00",
            "temp_c": 19.8,
            "temp_f": 67.6,
            "is_day": 0,
            "condition": {
              "text": "Mist",
              "icon": "//cdn.weatherapi.com/weather/64x64/night/143.png",
              "code": 1030
            },
            "wind_mph": 5.6,
            "wind_kph": 9.0,
            "wind_degree": 75,
            "wind_dir": "ENE",
            "pressure_mb": 1010.0,
            "pressure_in": 29.81,
            "precip_mm": 0.0,
            "precip_in": 0.0,
            "snow_cm": 0.0,
            "humidity": 94,
            "cloud": 46,
            "feelslike_c": 19.8,
            "feelslike_f": 67.6,
            "windchill_c": 19.8,
            "windchill_f": 67.6,
            "heatindex_c": 19.8,
            "heatindex_f": 67.6,
            "dewpoint_c": 18.9,
            "dewpoint_f": 65.9,
            "will_it_rain": 0,
            "chance_of_rain": 0,
            "will_it_snow": 0,
            "chance_of_snow": 0,
            "vis_km": 2.0,
            "vis_miles": 1.0,
            "gust_mph": 9.7,
            "gust_kph": 15.6,
            "uv": 0
          },
          {
            "time_epoch": 1760401800,
            "time": "2025-10-14 06:00",
            "temp_c": 19.8,
            "temp_f": 67.7,
            "is_day": 1,
            "condition": {
              "text": "Mist",
              "icon": "//cdn.weatherapi.com/weather/64x64/day/143.png",
              "code": 1030
            },
            "wind_mph": 5.6,
            "wind_kph": 9.0,
            "wind_degree": 76,
            "wind_dir": "ENE",
            "pressure_mb": 1010.0,
            "pressure_in": 29.84,
            "precip_mm": 0.0,
            "precip_in": 0.0,
            "snow_cm": 0.0,
            "humidity": 95,
            "cloud": 50,
            "feelslike_c": 19.8,
            "feelslike_f": 67.7,
            "windchill_c": 19.8,
            "windchill_f": 67.7,
            "heatindex_c": 19.8,
            "heatindex_f": 67.7,
            "dewpoint_c": 19.0,
            "dewpoint_f": 66.1,
            "will_it_rain": 0,
            "chance_of_rain": 0,
            "will_it_snow": 0,
            "chance_of_snow": 0,
            "vis_km": 2.0,
            "vis_miles": 1.0,
            "gust_mph": 9.5,
            "gust_kph": 15.3,
            "uv": 0.0
          },
          {
            "time_epoch": 1760405400,
            "time": "2025-10-14 07:00",
            "temp_c": 21.2,
            "temp_f": 70.1,
            "is_day": 1,
            "condition": {
              "text": "Partly Cloudy ",
              "icon": "//cdn.weatherapi.com/weather/64x64/day/116.png",
              "code": 1003
            },
            "wind_mph": 6.7,
            "wind_kph": 10.8,
            "wind_degree": 78,
            "wind_dir": "ENE",
            "pressure_mb": 1011.0,
            "pressure_in": 29.85,
            "precip_mm": 0.0,
            "precip_in": 0.0,
            "snow_cm": 0.0,
            "humidity": 89,
            "cloud": 39,
            "feelslike_c": 21.2,
            "feelslike_f": 70.1,
            "windchill_c": 21.2,
            "windchill_f": 70.1,
            "heatindex_c": 24.2,
            "heatindex_f": 75.5,
            "dewpoint_c": 19.3,
            "dewpoint_f": 66.7,
            "will_it_rain": 0,
            "chance_of_rain": 0,
            "will_it_snow": 0,
            "chance_of_snow": 0,
            "vis_km": 10.0,
            "vis_miles": 6.0,
            "gust_mph": 9.3,
            "gust_kph": 15.0,
            "uv": 0.6
          },
          {
            "time_epoch": 1760409000,
            "time": "2025-10-14 08:00",
            "temp_c": 22.8,
            "temp_f": 73.0,
            "is_day": 1,
            "condition": {
              "text": "Partly Cloudy ",
              "icon": "//cdn.weatherapi.com/weather/64x64/day/116.png",
              "code": 1003
            },
            "wind_mph": 7.6,
            "wind_kph": 12.2,
            "wind_degree": 77,
            "wind_dir": "ENE",
            "pressure_mb": 1011.0,
            "pressure_in": 29.86,
            "precip_mm": 0.0,
            "precip_in": 0.0,
            "snow_cm": 0.0,
            "humidity": 80,
            "cloud": 33,
            "feelslike_c": 24.9,
            "feelslike_f": 76.9,
            "windchill_c": 22.8,
            "windchill_f": 73.0,
            "heatindex_c": 24.9,
            "heatindex_f": 76.9,
            "dewpoint_c": 19.2,
            "dewpoint_f": 66.6,
            "will_it_rain": 0,
            "chance_of_rain": 0,
            "will_it_snow": 0,
            "chance_of_snow": 0,
            "vis_km": 10.0,
            "vis_miles": 6.0,
            "gust_mph": 9.4,
            "gust_kph": 15.2,
            "uv": 2.4
          },
          {
            "time_epoch": 1760412600,
            "time": "2025-10-14 09:00",
            "temp_c": 24.3,
            "temp_f": 75.8,
            "is_day": 1,
            "condition": {
              "text": "Partly Cloudy ",
              "icon": "//cdn.weatherapi.com/weather/64x64/day/116.png",
              "code": 1003
            },
            "wind_mph": 8.1,
            "wind_kph": 13.0,
            "wind_degree": 82,
            "wind_dir": "E",
            "pressure_mb": 1011.0,
            "pressure_in": 29.86,
            "precip_mm": 0.0,
            "precip_in": 0.0,
            "snow_cm": 0.0,
            "humidity": 73,
            "cloud": 62,
            "feelslike_c": 26.0,
            "feelslike_f": 78.9,
            "windchill_c": 24.3,
            "windchill_f": 75.8,
            "heatindex_c": 26.0,
            "heatindex_f": 78.9,
            "dewpoint_c": 19.2,
            "dewpoint_f": 66.6,
            "will_it_rain": 0,
            "chance_of_rain": 0,
            "will_it_snow": 0,
            "chance_of_snow": 0,
            "vis_km": 10.0,
            "vis_miles": 6.0,
            "gust_mph": 9.3,
            "gust_kph": 14.9,
            "uv": 5.3
          },
          {
            "time_epoch": 1760416200,
            "time": "2025-10-14 10:00",
            "temp_c": 25.7,
            "temp_f": 78.2,
            "is_day": 1,
            "condition": {
              "text": "Patchy rain nearby",
              "icon": "//cdn.weatherapi.com/weather/64x64/day/176.png",
              "code": 1063
            },
            "wind_mph": 8.7,
            "wind_kph": 14.0,
            "wind_degree": 89,
            "wind_dir": "E",
            "pressure_mb": 1010.0,
            "pressure_in": 29.84,
            "precip_mm": 0.04,
            "precip_in": 0.0,
            "snow_cm": 0.0,
            "humidity": 68,
            "cloud": 72,
            "feelslike_c": 27.3,
            "feelslike_f": 81.1,
            "windchill_c": 25.7,
            "windchill_f": 78.2,
            "heatindex_c": 27.3,
            "heatindex_f": 81.1,
            "dewpoint_c": 19.3,
            "dewpoint_f": 66.7,
            "will_it_rain": 1,
            "chance_of_rain": 73,
            "will_it_snow": 0,
            "chance_of_snow": 0,
            "vis_km": 10.0,
            "vis_miles": 6.0,
            "gust_mph": 10.0,
            "gust_kph": 16.2,
            "uv": 8.7
          },
          {
            "time_epoch": 1760419800,
            "time": "2025-10-14 11:00",
            "temp_c": 26.5,
            "temp_f": 79.6,
            "is_day": 1,
            "condition": {
              "text": "Patchy rain nearby",
              "icon": "//cdn.weatherapi.com/weather/64x64/day/176.png",
              "code": 1063
            },
            "wind_mph": 8.9,
            "wind_kph": 14.4,
            "wind_degree": 93,
            "wind_dir": "E",
            "pressure_mb": 1009.0,
            "pressure_in": 29.8,
            "precip_mm": 0.12,
            "precip_in": 0.0,
            "snow_cm": 0.0,
            "humidity": 64,
            "cloud": 90,
            "feelslike_c": 28.0,
            "feelslike_f": 82.4,
            "windchill_c": 26.5,
            "windchill_f": 79.6,
            "heatindex_c": 28.0,
            "heatindex_f": 82.4,
            "dewpoint_c": 19.2,
            "dewpoint_f": 66.5,
            "will_it_rain": 1,
            "chance_of_rain": 100,
            "will_it_snow": 0,
            "chance_of_snow": 0,
            "vis_km": 10.0,
            "vis_miles": 6.0,
            "gust_mph": 10.3,
            "gust_kph": 16.6,
            "uv": 11.2
          },
          {
            "time_epoch": 1760423400,
            "time": "2025-10-14 12:00",
            "temp_c": 26.8,
            "temp_f": 80.3,
            "is_day": 1,
            "condition": {
              "text": "Patchy rain nearby",
              "icon": "//cdn.weatherapi.com/weather/64x64/day/176.png",
              "code": 1063
            },
            "wind_mph": 9.6,
            "wind_kph": 15.5,
            "wind_degree": 102,
            "wind_dir": "ESE",
            "pressure_mb": 1008.0,
            "pressure_in": 29.76,
            "precip_mm": 0.11,
            "precip_in": 0.0,
            "snow_cm": 0.0,
            "humidity": 62,
            "cloud": 51,
            "feelslike_c": 28.3,
            "feelslike_f": 83.0,
            "windchill_c": 26.8,
            "windchill_f": 80.3,
            "heatindex_c": 28.3,
            "heatindex_f": 83.0,
            "dewpoint_c": 19.1,
            "dewpoint_f": 66.3,
            "will_it_rain": 1,
            "chance_of_rain": 100,
            "will_it_snow": 0,
            "chance_of_snow": 0,
            "vis_km": 10.0,
            "vis_miles": 6.0,
            "gust_mph": 11.1,
            "gust_kph": 17.8,
            "uv": 10.7
          },
          {
            "time_epoch": 1760427000,
            "time": "2025-10-14 13:00",
            "temp_c": 26.8,
            "temp_f": 80.2,
            "is_day": 1,
            "condition": {
              "text": "Patchy rain nearby",
              "icon": "//cdn.weatherapi.com/weather/64x64/day/176.png",
              "code": 1063
            },
            "wind_mph": 9.4,
            "wind_kph": 15.1,
            "wind_degree": 109,
            "wind_dir": "ESE",
            "pressure_mb": 1006.0,
            "pressure_in": 29.72,
            "precip_mm": 0.08,
            "precip_in": 0.0,
            "snow_cm": 0.0,
            "humidity": 63,
            "cloud": 71,
            "feelslike_c": 28.3,
            "feelslike_f": 82.9,
            "windchill_c": 26.8,
            "windchill_f": 80.2,
            "heatindex_c": 28.3,
            "heatindex_f": 82.9,
            "dewpoint_c": 19.1,
            "dewpoint_f": 66.3,
            "will_it_rain": 1,
            "chance_of_rain": 100,
            "will_it_snow": 0,
            "chance_of_snow": 0,
            "vis_km": 10.0,
            "vis_miles": 6.0,
            "gust_mph": 11.3,
            "gust_kph": 18.1,
            "uv": 7.5
          },
          {
            "time_epoch": 1760430600,
            "time": "2025-10-14 14:00",
            "temp_c": 26.6,
            "temp_f": 79.9,
            "is_day": 1,
            "condition": {
              "text": "Patchy rain nearby",
              "icon": "//cdn.weatherapi.com/weather/64x64/day/176.png",
              "code": 1063
            },
            "wind_mph": 8.9,
            "wind_kph": 14.4,
            "wind_degree": 113,
            "wind_dir": "ESE",
            "pressure_mb": 1006.0,
            "pressure_in": 29.7,
            "precip_mm": 0.14,
            "precip_in": 0.01,
            "snow_cm": 0.0,
            "humidity": 64,
            "cloud": 88,
            "feelslike_c": 28.2,
            "feelslike_f": 82.7,
            "windchill_c": 26.6,
            "windchill_f": 79.9,
            "heatindex_c": 28.2,
            "heatindex_f": 82.7,
            "dewpoint_c": 19.3,
            "dewpoint_f": 66.7,
            "will_it_rain": 1,
            "chance_of_rain": 100,
            "will_it_snow": 0,
            "chance_of_snow": 0,
            "vis_km": 10.0,
            "vis_miles": 6.0,
            "gust_mph": 11.1,
            "gust_kph": 17.9,
            "uv": 5.7
          },
          {
            "time_epoch": 1760434200,
            "time": "2025-10-14 15:00",
            "temp_c": 25.4,
            "temp_f": 77.7,
            "is_day": 1,
            "condition": {
              "text": "Light rain shower",
              "icon": "//cdn.weatherapi.com/weather/64x64/day/353.png",
              "code": 1240
            },
            "wind_mph": 8.9,
            "wind_kph": 14.4,
            "wind_degree": 118,
            "wind_dir": "ESE",
            "pressure_mb": 1006.0,
            "pressure_in": 29.71,
            "precip_mm": 1.03,
            "precip_in": 0.04,
            "snow_cm": 0.0,
            "humidity": 70,
            "cloud": 86,
            "feelslike_c": 27.0,
            "feelslike_f": 80.6,
            "windchill_c": 25.4,
            "windchill_f": 77.7,
            "heatindex_c": 27.0,
            "heatindex_f": 80.6,
            "dewpoint_c": 19.5,
            "dewpoint_f": 67.1,
            "will_it_rain": 1,
            "chance_of_rain": 100,
            "will_it_snow": 0,
            "chance_of_snow": 0,
            "vis_km": 10.0,
            "vis_miles": 6.0,
            "gust_mph": 12.3,
            "gust_kph": 19.8,
            "uv": 3.4
          },
          {
            "time_epoch": 1760437800,
            "time": "2025-10-14 16:00",
            "temp_c": 24.6,
            "temp_f": 76.4,
            "is_day": 1,
            "condition": {
              "text": "Patchy rain nearby",
              "icon": "//cdn.weatherapi.com/weather/64x64/day/176.png",
              "code": 1063
            },
            "wind_mph": 6.9,
            "wind_kph": 11.2,
            "wind_degree": 110,
            "wind_dir": "ESE",
            "pressure_mb": 1006.0,
            "pressure_in": 29.71,
            "precip_mm": 0.16,
            "precip_in": 0.01,
            "snow_cm": 0.0,
            "humidity": 73,
            "cloud": 88,
            "feelslike_c": 26.4,
            "feelslike_f": 79.4,
            "windchill_c": 24.6,
            "windchill_f": 76.4,
            "heatindex_c": 26.4,
            "heatindex_f": 79.4,
            "dewpoint_c": 19.6,
            "dewpoint_f": 67.2,
            "will_it_rain": 1,
            "chance_of_rain": 100,
            "will_it_snow": 0,
            "chance_of_snow": 0,
            "vis_km": 9.0,
            "vis_miles": 5.0,
            "gust_mph": 10.6,
            "gust_kph": 17.1,
            "uv": 1.5
          },
          {
            "time_epoch": 1760441400,
            "time": "2025-10-14 17:00",
            "temp_c": 24.5,
            "temp_f": 76.0,
            "is_day": 1,
            "condition": {
              "text": "Patchy rain nearby",
              "icon": "//cdn.weatherapi.com/weather/64x64/day/176.png",
              "code": 1063
            },
            "wind_mph": 6.9,
            "wind_kph": 11.2,
            "wind_degree": 106,
            "wind_dir": "ESE",
            "pressure_mb": 1007.0,
            "pressure_in": 29.73,
            "precip_mm": 0.48,
            "precip_in": 0.02,
            "snow_cm": 0.0,
            "humidity": 75,
            "cloud": 89,
            "feelslike_c": 26.3,
            "feelslike_f": 79.3,
            "windchill_c": 24.5,
            "windchill_f": 76.0,
            "heatindex_c": 26.3,
            "heatindex_f": 79.3,
            "dewpoint_c": 19.9,
            "dewpoint_f": 67.7,
            "will_it_rain": 1,
            "chance_of_rain": 100,
            "will_it_snow": 0,
            "chance_of_snow": 0,
            "vis_km": 9.0,
            "vis_miles": 5.0,
            "gust_mph": 10.7,
            "gust_kph": 17.2,
            "uv": 0.3
          },
          {
            "time_epoch": 1760445000,
            "time": "2025-10-14 18:00",
            "temp_c": 22.7,
            "temp_f": 72.8,
            "is_day": 0,
            "condition": {
              "text": "Patchy rain nearby",
              "icon": "//cdn.weatherapi.com/weather/64x64/night/176.png",
              "code": 1063
            },
            "wind_mph": 8.5,
            "wind_kph": 13.7,
            "wind_degree": 118,
            "wind_dir": "ESE",
            "pressure_mb": 1008.0,
            "pressure_in": 29.76,
            "precip_mm": 0.75,
            "precip_in": 0.03,
            "snow_cm": 0.0,
            "humidity": 84,
            "cloud": 78,
            "feelslike_c": 24.9,
            "feelslike_f": 76.8,
            "windchill_c": 22.7,
            "windchill_f": 72.8,
            "heatindex_c": 24.9,
            "heatindex_f": 76.8,
            "dewpoint_c": 19.9,
            "dewpoint_f": 67.7,
            "will_it_rain": 1,
            "chance_of_rain": 100,
            "will_it_snow": 0,
            "chance_of_snow": 0,
            "vis_km": 9.0,
            "vis_miles": 5.0,
            "gust_mph": 14.9,
            "gust_kph": 24.0,
            "uv": 0
          },
          {
            "time_epoch": 1760448600,
            "time": "2025-10-14 19:00",
            "temp_c": 21.8,
            "temp_f": 71.2,
            "is_day": 0,
            "condition": {
              "text": "Patchy rain nearby",
              "icon": "//cdn.weatherapi.com/weather/64x64/night/176.png",
              "code": 1063
            },
            "wind_mph": 7.2,
            "wind_kph": 11.5,
            "wind_degree": 125,
            "wind_dir": "SE",
            "pressure_mb": 1009.0,
            "pressure_in": 29.79,
            "precip_mm": 0.06,
            "precip_in": 0.0,
            "snow_cm": 0.0,
            "humidity": 89,
            "cloud": 88,
            "feelslike_c": 21.8,
            "feelslike_f": 71.2,
            "windchill_c": 21.8,
            "windchill_f": 71.2,
            "heatindex_c": 24.4,
            "heatindex_f": 75.9,
            "dewpoint_c": 19.8,
            "dewpoint_f": 67.7,
            "will_it_rain": 1,
            "chance_of_rain": 100,
            "will_it_snow": 0,
            "chance_of_snow": 0,
            "vis_km": 10.0,
            "vis_miles": 6.0,
            "gust_mph": 13.0,
            "gust_kph": 20.8,
            "uv": 0
          },
          {
            "time_epoch": 1760452200,
            "time": "2025-10-14 20:00",
            "temp_c": 21.6,
            "temp_f": 70.8,
            "is_day": 0,
            "condition": {
              "text": "Partly Cloudy ",
              "icon": "//cdn.weatherapi.com/weather/64x64/night/116.png",
              "code": 1003
            },
            "wind_mph": 5.8,
            "wind_kph": 9.4,
            "wind_degree": 123,
            "wind_dir": "ESE",
            "pressure_mb": 1009.0,
            "pressure_in": 29.81,
            "precip_mm": 0.0,
            "precip_in": 0.0,
            "snow_cm": 0.0,
            "humidity": 89,
            "cloud": 43,
            "feelslike_c": 21.6,
            "feelslike_f": 70.8,
            "windchill_c": 21.6,
            "windchill_f": 70.8,
            "heatindex_c": 24.3,
            "heatindex_f": 75.8,
            "dewpoint_c": 19.7,
            "dewpoint_f": 67.4,
            "will_it_rain": 0,
            "chance_of_rain": 0,
            "will_it_snow": 0,
            "chance_of_snow": 0,
            "vis_km": 10.0,
            "vis_miles": 6.0,
            "gust_mph": 10.4,
            "gust_kph": 16.8,
            "uv": 0
          },
          {
            "time_epoch": 1760455800,
            "time": "2025-10-14 21:00",
            "temp_c": 21.3,
            "temp_f": 70.4,
            "is_day": 0,
            "condition": {
              "text": "Clear ",
              "icon": "//cdn.weatherapi.com/weather/64x64/night/113.png",
              "code": 1000
            },
            "wind_mph": 4.9,
            "wind_kph": 7.9,
            "wind_degree": 115,
            "wind_dir": "ESE",
            "pressure_mb": 1010.0,
            "pressure_in": 29.82,
            "precip_mm": 0.0,
            "precip_in": 0.0,
            "snow_cm": 0.0,
            "humidity": 89,
            "cloud": 14,
            "feelslike_c": 21.3,
            "feelslike_f": 70.4,
            "windchill_c": 21.3,
            "windchill_f": 70.4,
            "heatindex_c": 24.2,
            "heatindex_f": 75.6,
            "dewpoint_c": 19.5,
            "dewpoint_f": 67.1,
            "will_it_rain": 0,
            "chance_of_rain": 0,
            "will_it_snow": 0,
            "chance_of_snow": 0,
            "vis_km": 10.0,
            "vis_miles": 6.0,
            "gust_mph": 8.8,
            "gust_kph": 14.2,
            "uv": 0
          },
          {
            "time_epoch": 1760459400,
            "time": "2025-10-14 22:00",
            "temp_c": 20.9,
            "temp_f": 69.6,
            "is_day": 0,
            "condition": {
              "text": "Clear ",
              "icon": "//cdn.weatherapi.com/weather/64x64/night/113.png",
              "code": 1000
            },
            "wind_mph": 5.6,
            "wind_kph": 9.0,
            "wind_degree": 124,
            "wind_dir": "SE",
            "pressure_mb": 1010.0,
            "pressure_in": 29.82,
            "precip_mm": 0.0,
            "precip_in": 0.0,
            "snow_cm": 0.0,
            "humidity": 90,
            "cloud": 20,
            "feelslike_c": 20.9,
            "feelslike_f": 69.6,
            "windchill_c": 20.9,
            "windchill_f": 69.6,
            "heatindex_c": 20.9,
            "heatindex_f": 69.6,
            "dewpoint_c": 19.3,
            "dewpoint_f": 66.7,
            "will_it_rain": 0,
            "chance_of_rain": 0,
            "will_it_snow": 0,
            "chance_of_snow": 0,
            "vis_km": 10.0,
            "vis_miles": 6.0,
            "gust_mph": 9.8,
            "gust_kph": 15.7,
            "uv": 0
          },
          {
            "time_epoch": 1760463000,
            "time": "2025-10-14 23:00",
            "temp_c": 20.5,
            "temp_f": 68.9,
            "is_day": 0,
            "condition": {
              "text": "Partly Cloudy ",
              "icon": "//cdn.weatherapi.com/weather/64x64/night/116.png",
              "code": 1003
            },
            "wind_mph": 5.1,
            "wind_kph": 8.3,
            "wind_degree": 116,
            "wind_dir": "ESE",
            "pressure_mb": 1009.0,
            "pressure_in": 29.81,
            "precip_mm": 0.0,
            "precip_in": 0.0,
            "snow_cm": 0.0,
            "humidity": 92,
            "cloud": 29,
            "feelslike_c": 20.5,
            "feelslike_f": 68.9,
            "windchill_c": 20.5,
            "windchill_f": 68.9,
            "heatindex_c": 20.5,
            "heatindex_f": 68.9,
            "dewpoint_c": 19.2,
            "dewpoint_f": 66.5,
            "will_it_rain": 0,
            "chance_of_rain": 0,
            "will_it_snow": 0,
            "chance_of_snow": 0,
            "vis_km": 10.0,
            "vis_miles": 6.0,
            "gust_mph": 8.8,
            "gust_kph": 14.1,
            "uv": 0
          }
        ]
      },
      {
        "date": "2025-10-15",
        "date_epoch": 1760486400,
        "day": {
          "maxtemp_c": 27.0,
          "maxtemp_f": 80.5,
          "mintemp_c": 19.5,
          "mintemp_f": 67.0,
          "avgtemp_c": 22.6,
          "avgtemp_f": 72.7,
          "maxwind_mph": 8.9,
          "maxwind_kph": 14.4,
          "totalprecip_mm": 0.2,
          "totalprecip_in": 0.01,
          "totalsnow_cm": 0.0,
          "avgvis_km": 7.8,
          "avgvis_miles": 4.0,
          "avghumidity": 80,
          "daily_will_it_rain": 1,
          "daily_chance_of_rain": 88,
          "daily_will_it_snow": 0,
          "daily_chance_of_snow": 0,
          "condition": {
            "text": "Patchy rain nearby",
            "icon": "//cdn.weatherapi.com/weather/64x64/day/176.png",
            "code": 1063
          },
          "uv": 2.3
        },
        "astro": {
          "moonrise": "12:56 AM",
          "moonset": "02:03 PM",
          "sunrise": "06:10 AM",
          "sunset": "06:01 PM",
          "moon_phase": "Waning Crescent",
          "moon_illumination": 37,
          "is_moon_up": 1,
          "is_sun_up": 0
        },
        "hour": [
          {
            "time_epoch": 1760466600,
            "time": "2025-10-15 00:00",
            "temp_c": 20.3,
            "temp_f": 68.5,
            "is_day": 0,
            "condition": {
              "text": "Partly Cloudy ",
              "icon": "//cdn.weatherapi.com/weather/64x64/night/116.png",
              "code": 1003
            },
            "wind_mph": 5.8,
            "wind_kph": 9.4,
            "wind_degree": 103,
            "wind_dir": "ESE",
            "pressure_mb": 1009.0,
            "pressure_in": 29.79,
            "precip_mm": 0.0,
            "precip_in": 0.0,
            "snow_cm": 0.0,
            "humidity": 94,
            "cloud": 43,
            "feelslike_c": 20.3,
            "feelslike_f": 68.5,
            "windchill_c": 20.3,
            "windchill_f": 68.5,
            "heatindex_c": 20.3,
            "heatindex_f": 68.5,
            "dewpoint_c": 19.3,
            "dewpoint_f": 66.7,
            "will_it_rain": 0,
            "chance_of_rain": 0,
            "will_it_snow": 0,
            "chance_of_snow": 0,
            "vis_km": 10.0,
            "vis_miles": 6.0,
            "gust_mph": 9.8,
            "gust_kph": 15.8,
            "uv": 0
          },
          {
            "time_epoch": 1760470200,
            "time": "2025-10-15 01:00",
            "temp_c": 20.0,
            "temp_f": 68.1,
            "is_day": 0,
            "condition": {
              "text": "Mist",
              "icon": "//cdn.weatherapi.com/weather/64x64/night/143.png",
              "code": 1030
            },
            "wind_mph": 5.6,
            "wind_kph": 9.0,
            "wind_degree": 111,
            "wind_dir": "ESE",
            "pressure_mb": 1008.0,
            "pressure_in": 29.78,
            "precip_mm": 0.0,
            "precip_in": 0.0,
            "snow_cm": 0.0,
            "humidity": 95,
            "cloud": 58,
            "feelslike_c": 20.1,
            "feelslike_f": 68.1,
            "windchill_c": 20.1,
            "windchill_f": 68.1,
            "heatindex_c": 20.1,
            "heatindex_f": 68.1,
            "dewpoint_c": 19.3,
            "dewpoint_f": 66.7,
            "will_it_rain": 0,
            "chance_of_rain": 0,
            "will_it_snow": 0,
            "chance_of_snow": 0,
            "vis_km": 2.0,
            "vis_miles": 1.0,
            "gust_mph": 9.2,
            "gust_kph": 14.8,
            "uv": 0
          },
          {
            "time_epoch": 1760473800,
            "time": "2025-10-15 02:00",
            "temp_c": 19.9,
            "temp_f": 67.8,
            "is_day": 0,
            "condition": {
              "text": "Mist",
              "icon": "//cdn.weatherapi.com/weather/64x64/night/143.png",
              "code": 1030
            },
            "wind_mph": 5.6,
            "wind_kph": 9.0,
            "wind_degree": 100,
            "wind_dir": "E",
            "pressure_mb": 1008.0,
            "pressure_in": 29.76,
            "precip_mm": 0.0,
            "precip_in": 0.0,
            "snow_cm": 0.0,
            "humidity": 96,
            "cloud": 64,
            "feelslike_c": 19.9,
            "feelslike_f": 67.8,
            "windchill_c": 19.9,
            "windchill_f": 67.8,
            "heatindex_c": 19.9,
            "heatindex_f": 67.8,
            "dewpoint_c": 19.3,
            "dewpoint_f": 66.7,
            "will_it_rain": 0,
            "chance_of_rain": 0,
            "will_it_snow": 0,
            "chance_of_snow": 0,
            "vis_km": 2.0,
            "vis_miles": 1.0,
            "gust_mph": 9.1,
            "gust_kph": 14.7,
            "uv": 0
          },
          {
            "time_epoch": 1760477400,
            "time": "2025-10-15 03:00",
            "temp_c": 19.8,
            "temp_f": 67.6,
            "is_day": 0,
            "condition": {
              "text": "Mist",
              "icon": "//cdn.weatherapi.com/weather/64x64/night/143.png",
              "code": 1030
            },
            "wind_mph": 5.1,
            "wind_kph": 8.3,
            "wind_degree": 101,
            "wind_dir": "ESE",
            "pressure_mb": 1008.0,
            "pressure_in": 29.76,
            "precip_mm": 0.0,
            "precip_in": 0.0,
            "snow_cm": 0.0,
            "humidity": 97,
            "cloud": 69,
            "feelslike_c": 19.8,
            "feelslike_f": 67.6,
            "windchill_c": 19.8,
            "windchill_f": 67.6,
            "heatindex_c": 19.8,
            "heatindex_f": 67.6,
            "dewpoint_c": 19.3,
            "dewpoint_f": 66.7,
            "will_it_rain": 0,
            "chance_of_rain": 0,
            "will_it_snow": 0,
            "chance_of_snow": 0,
            "vis_km": 2.0,
            "vis_miles": 1.0,
            "gust_mph": 8.3,
            "gust_kph": 13.3,
            "uv": 0
          },
          {
            "time_epoch": 1760481000,
            "time": "2025-10-15 04:00",
            "temp_c": 19.7,
            "temp_f": 67.4,
            "is_day": 0,
            "condition": {
              "text": "Fog",
              "icon": "//cdn.weatherapi.com/weather/64x64/night/248.png",
              "code": 1135
            },
            "wind_mph": 5.1,
            "wind_kph": 8.3,
            "wind_degree": 93,
            "wind_dir": "E",
            "pressure_mb": 1008.0,
            "pressure_in": 29.76,
            "precip_mm": 0.0,
            "precip_in": 0.0,
            "snow_cm": 0.0,
            "humidity": 97,
            "cloud": 100,
            "feelslike_c": 19.7,
            "feelslike_f": 67.4,
            "windchill_c": 19.7,
            "windchill_f": 67.4,
            "heatindex_c": 19.7,
            "heatindex_f": 67.4,
            "dewpoint_c": 19.2,
            "dewpoint_f": 66.5,
            "will_it_rain": 0,
            "chance_of_rain": 0,
            "will_it_snow": 0,
            "chance_of_snow": 0,
            "vis_km": 0.0,
            "vis_miles": 0.0,
            "gust_mph": 8.3,
            "gust_kph": 13.4,
            "uv": 0
          },
          {
            "time_epoch": 1760484600,
            "time": "2025-10-15 05:00",
            "temp_c": 19.5,
            "temp_f": 67.2,
            "is_day": 0,
            "condition": {
              "text": "Fog",
              "icon": "//cdn.weatherapi.com/weather/64x64/night/248.png",
              "code": 1135
            },
            "wind_mph": 6.0,
            "wind_kph": 9.7,
            "wind_degree": 94,
            "wind_dir": "E",
            "pressure_mb": 1008.0,
            "pressure_in": 29.78,
            "precip_mm": 0.0,
            "precip_in": 0.0,
            "snow_cm": 0.0,
            "humidity": 97,
            "cloud": 100,
            "feelslike_c": 19.5,
            "feelslike_f": 67.2,
            "windchill_c": 19.5,
            "windchill_f": 67.2,
            "heatindex_c": 19.5,
            "heatindex_f": 67.2,
            "dewpoint_c": 19.1,
            "dewpoint_f": 66.4,
            "will_it_rain": 0,
            "chance_of_rain": 0,
            "will_it_snow": 0,
            "chance_of_snow": 0,
            "vis_km": 0.0,
            "vis_miles": 0.0,
            "gust_mph": 9.8,
            "gust_kph": 15.8,
            "uv": 0
          },
          {
            "time_epoch": 1760488200,
            "time": "2025-10-15 06:00",
            "temp_c": 19.5,
            "temp_f": 67.0,
            "is_day": 1,
            "condition": {
              "text": "Fog",
              "icon": "//cdn.weatherapi.com/weather/64x64/day/248.png",
              "code": 1135
            },
            "wind_mph": 6.5,
            "wind_kph": 10.4,
            "wind_degree": 97,
            "wind_dir": "E",
            "pressure_mb": 1009.0,
            "pressure_in": 29.81,
            "precip_mm": 0.0,
            "precip_in": 0.0,
            "snow_cm": 0.0,
            "humidity": 98,
            "cloud": 100,
            "feelslike_c": 19.5,
            "feelslike_f": 67.0,
            "windchill_c": 19.5,
            "windchill_f": 67.0,
            "heatindex_c": 19.5,
            "heatindex_f": 67.0,
            "dewpoint_c": 19.1,
            "dewpoint_f": 66.3,
            "will_it_rain": 0,
            "chance_of_rain": 0,
            "will_it_snow": 0,
            "chance_of_snow": 0,
            "vis_km": 0.0,
            "vis_miles": 0.0,
            "gust_mph": 10.3,
            "gust_kph": 16.5,
            "uv": 0.0
          },
          {
            "time_epoch": 1760491800,
            "time": "2025-10-15 07:00",
            "temp_c": 20.1,
            "temp_f": 68.3,
            "is_day": 1,
            "condition": {
              "text": "Cloudy ",
              "icon": "//cdn.weatherapi.com/weather/64x64/day/119.png",
              "code": 1006
            },
            "wind_mph": 7.2,
            "wind_kph": 11.5,
            "wind_degree": 100,
            "wind_dir": "E",
            "pressure_mb": 1010.0,
            "pressure_in": 29.83,
            "precip_mm": 0.0,
            "precip_in": 0.0,
            "snow_cm": 0.0,
            "humidity": 94,
            "cloud": 83,
            "feelslike_c": 20.2,
            "feelslike_f": 68.3,
            "windchill_c": 20.2,
            "windchill_f": 68.3,
            "heatindex_c": 20.2,
            "heatindex_f": 68.3,
            "dewpoint_c": 19.1,
            "dewpoint_f": 66.5,
            "will_it_rain": 0,
            "chance_of_rain": 0,
            "will_it_snow": 0,
            "chance_of_snow": 0,
            "vis_km": 10.0,
            "vis_miles": 6.0,
            "gust_mph": 9.8,
            "gust_kph": 15.8,
            "uv": 0.4
          },
          {
            "time_epoch": 1760495400,
            "time": "2025-10-15 08:00",
            "temp_c": 21.5,
            "temp_f": 70.6,
            "is_day": 1,
            "condition": {
              "text": "Partly Cloudy ",
              "icon": "//cdn.weatherapi.com/weather/64x64/day/116.png",
              "code": 1003
            },
            "wind_mph": 7.6,
            "wind_kph": 12.2,
            "wind_degree": 99,
            "wind_dir": "E",
            "pressure_mb": 1010.0,
            "pressure_in": 29.83,
            "precip_mm": 0.0,
            "precip_in": 0.0,
            "snow_cm": 0.0,
            "humidity": 87,
            "cloud": 36,
            "feelslike_c": 21.5,
            "feelslike_f": 70.6,
            "windchill_c": 21.5,
            "windchill_f": 70.6,
            "heatindex_c": 24.3,
            "heatindex_f": 75.7,
            "dewpoint_c": 19.1,
            "dewpoint_f": 66.4,
            "will_it_rain": 0,
            "chance_of_rain": 0,
            "will_it_snow": 0,
            "chance_of_snow": 0,
            "vis_km": 10.0,
            "vis_miles": 6.0,
            "gust_mph": 9.4,
            "gust_kph": 15.2,
            "uv": 1.7
          },
          {
            "time_epoch": 1760499000,
            "time": "2025-10-15 09:00",
            "temp_c": 23.2,
            "temp_f": 73.8,
            "is_day": 1,
            "condition": {
              "text": "Sunny",
              "icon": "//cdn.weatherapi.com/weather/64x64/day/113.png",
              "code": 1000
            },
            "wind_mph": 7.8,
            "wind_kph": 12.6,
            "wind_degree": 105,
            "wind_dir": "ESE",
            "pressure_mb": 1010.0,
            "pressure_in": 29.84,
            "precip_mm": 0.0,
            "precip_in": 0.0,
            "snow_cm": 0.0,
            "humidity": 76,
            "cloud": 25,
            "feelslike_c": 25.2,
            "feelslike_f": 77.4,
            "windchill_c": 23.2,
            "windchill_f": 73.8,
            "heatindex_c": 25.2,
            "heatindex_f": 77.4,
            "dewpoint_c": 18.8,
            "dewpoint_f": 65.8,
            "will_it_rain": 0,
            "chance_of_rain": 0,
            "will_it_snow": 0,
            "chance_of_snow": 0,
            "vis_km": 10.0,
            "vis_miles": 6.0,
            "gust_mph": 9.0,
            "gust_kph": 14.5,
            "uv": 3.8
          },
          {
            "time_epoch": 1760502600,
            "time": "2025-10-15 10:00",
            "temp_c": 24.7,
            "temp_f": 76.5,
            "is_day": 1,
            "condition": {
              "text": "Sunny",
              "icon": "//cdn.weatherapi.com/weather/64x64/day/113.png",
              "code": 1000
            },
            "wind_mph": 7.8,
            "wind_kph": 12.6,
            "wind_degree": 101,
            "wind_dir": "ESE",
            "pressure_mb": 1010.0,
            "pressure_in": 29.83,
            "precip_mm": 0.0,
            "precip_in": 0.0,
            "snow_cm": 0.0,
            "humidity": 66,
            "cloud": 14,
            "feelslike_c": 26.2,
            "feelslike_f": 79.1,
            "windchill_c": 24.7,
            "windchill_f": 76.5,
            "heatindex_c": 26.2,
            "heatindex_f": 79.1,
            "dewpoint_c": 17.8,
            "dewpoint_f": 64.1,
            "will_it_rain": 0,
            "chance_of_rain": 0,
            "will_it_snow": 0,
            "chance_of_snow": 0,
            "vis_km": 10.0,
            "vis_miles": 6.0,
            "gust_mph": 9.0,
            "gust_kph": 14.5,
            "uv": 6.9
          },
          {
            "time_epoch": 1760506200,
            "time": "2025-10-15 11:00",
            "temp_c": 25.9,
            "temp_f": 78.6,
            "is_day": 1,
            "condition": {
              "text": "Sunny",
              "icon": "//cdn.weatherapi.com/weather/64x64/day/113.png",
              "code": 1000
            },
            "wind_mph": 8.3,
            "wind_kph": 13.3,
            "wind_degree": 98,
            "wind_dir": "E",
            "pressure_mb": 1009.0,
            "pressure_in": 29.79,
            "precip_mm": 0.0,
            "precip_in": 0.0,
            "snow_cm": 0.0,
            "humidity": 58,
            "cloud": 15,
            "feelslike_c": 27.0,
            "feelslike_f": 80.5,
            "windchill_c": 25.9,
            "windchill_f": 78.6,
            "heatindex_c": 27.0,
            "heatindex_f": 80.5,
            "dewpoint_c": 17.0,
            "dewpoint_f": 62.7,
            "will_it_rain": 0,
            "chance_of_rain": 0,
            "will_it_snow": 0,
            "chance_of_snow": 0,
            "vis_km": 10.0,
            "vis_miles": 6.0,
            "gust_mph": 9.5,
            "gust_kph": 15.3,
            "uv": 9.7
          },
          {
            "time_epoch": 1760509800,
            "time": "2025-10-15 12:00",
            "temp_c": 26.7,
            "temp_f": 80.0,
            "is_day": 1,
            "condition": {
              "text": "Partly Cloudy ",
              "icon": "//cdn.weatherapi.com/weather/64x64/day/116.png",
              "code": 1003
            },
            "wind_mph": 8.7,
            "wind_kph": 14.0,
            "wind_degree": 100,
            "wind_dir": "E",
            "pressure_mb": 1008.0,
            "pressure_in": 29.76,
            "precip_mm": 0.0,
            "precip_in": 0.0,
            "snow_cm": 0.0,
            "humidity": 55,
            "cloud": 29,
            "feelslike_c": 27.6,
            "feelslike_f": 81.7,
            "windchill_c": 26.7,
            "windchill_f": 80.0,
            "heatindex_c": 27.6,
            "heatindex_f": 81.7,
            "dewpoint_c": 16.9,
            "dewpoint_f": 62.5,
            "will_it_rain": 0,
            "chance_of_rain": 0,
            "will_it_snow": 0,
            "chance_of_snow": 0,
            "vis_km": 10.0,
            "vis_miles": 6.0,
            "gust_mph": 10.0,
            "gust_kph": 16.2,
            "uv": 10.5
          },
          {
            "time_epoch": 1760513400,
            "time": "2025-10-15 13:00",
            "temp_c": 27.0,
            "temp_f": 80.5,
            "is_day": 1,
            "condition": {
              "text": "Patchy rain nearby",
              "icon": "//cdn.weatherapi.com/weather/64x64/day/176.png",
              "code": 1063
            },
            "wind_mph": 8.9,
            "wind_kph": 14.4,
            "wind_degree": 103,
            "wind_dir": "ESE",
            "pressure_mb": 1007.0,
            "pressure_in": 29.73,
            "precip_mm": 0.01,
            "precip_in": 0.0,
            "snow_cm": 0.0,
            "humidity": 55,
            "cloud": 78,
            "feelslike_c": 27.9,
            "feelslike_f": 82.3,
            "windchill_c": 27.0,
            "windchill_f": 80.5,
            "heatindex_c": 27.9,
            "heatindex_f": 82.3,
            "dewpoint_c": 17.2,
            "dewpoint_f": 62.9,
            "will_it_rain": 1,
            "chance_of_rain": 88,
            "will_it_snow": 0,
            "chance_of_snow": 0,
            "vis_km": 10.0,
            "vis_miles": 6.0,
            "gust_mph": 10.3,
            "gust_kph": 16.6,
            "uv": 9.9
          },
          {
            "time_epoch": 1760517000,
            "time": "2025-10-15 14:00",
            "temp_c": 26.8,
            "temp_f": 80.3,
            "is_day": 1,
            "condition": {
              "text": "Patchy rain nearby",
              "icon": "//cdn.weatherapi.com/weather/64x64/day/176.png",
              "code": 1063
            },
            "wind_mph": 8.7,
            "wind_kph": 14.0,
            "wind_degree": 105,
            "wind_dir": "ESE",
            "pressure_mb": 1006.0,
            "pressure_in": 29.71,
            "precip_mm": 0.01,
            "precip_in": 0.0,
            "snow_cm": 0.0,
            "humidity": 56,
            "cloud": 88,
            "feelslike_c": 27.9,
            "feelslike_f": 82.2,
            "windchill_c": 26.8,
            "windchill_f": 80.3,
            "heatindex_c": 27.9,
            "heatindex_f": 82.2,
            "dewpoint_c": 17.4,
            "dewpoint_f": 63.4,
            "will_it_rain": 1,
            "chance_of_rain": 83,
            "will_it_snow": 0,
            "chance_of_snow": 0,
            "vis_km": 10.0,
            "vis_miles": 6.0,
            "gust_mph": 10.2,
            "gust_kph": 16.4,
            "uv": 7.6
          },
          {
            "time_epoch": 1760520600,
            "time": "2025-10-15 15:00",
            "temp_c": 26.2,
            "temp_f": 79.2,
            "is_day": 1,
            "condition": {
              "text": "Patchy rain nearby",
              "icon": "//cdn.weatherapi.com/weather/64x64/day/176.png",
              "code": 1063
            },
            "wind_mph": 8.7,
            "wind_kph": 14.0,
            "wind_degree": 103,
            "wind_dir": "ESE",
            "pressure_mb": 1006.0,
            "pressure_in": 29.7,
            "precip_mm": 0.01,
            "precip_in": 0.0,
            "snow_cm": 0.0,
            "humidity": 60,
            "cloud": 83,
            "feelslike_c": 27.4,
            "feelslike_f": 81.4,
            "windchill_c": 26.2,
            "windchill_f": 79.2,
            "heatindex_c": 27.4,
            "heatindex_f": 81.4,
            "dewpoint_c": 17.8,
            "dewpoint_f": 64.1,
            "will_it_rain": 1,
            "chance_of_rain": 86,
            "will_it_snow": 0,
            "chance_of_snow": 0,
            "vis_km": 10.0,
            "vis_miles": 6.0,
            "gust_mph": 11.3,
            "gust_kph": 18.1,
            "uv": 4.1
          },
          {
            "time_epoch": 1760524200,
            "time": "2025-10-15 16:00",
            "temp_c": 25.4,
            "temp_f": 77.7,
            "is_day": 1,
            "condition": {
              "text": "Patchy rain nearby",
              "icon": "//cdn.weatherapi.com/weather/64x64/day/176.png",
              "code": 1063
            },
            "wind_mph": 8.5,
            "wind_kph": 13.7,
            "wind_degree": 98,
            "wind_dir": "E",
            "pressure_mb": 1006.0,
            "pressure_in": 29.71,
            "precip_mm": 0.06,
            "precip_in": 0.0,
            "snow_cm": 0.0,
            "humidity": 67,
            "cloud": 73,
            "feelslike_c": 26.9,
            "feelslike_f": 80.4,
            "windchill_c": 25.4,
            "windchill_f": 77.7,
            "heatindex_c": 26.9,
            "heatindex_f": 80.4,
            "dewpoint_c": 18.8,
            "dewpoint_f": 65.8,
            "will_it_rain": 1,
            "chance_of_rain": 100,
            "will_it_snow": 0,
            "chance_of_snow": 0,
            "vis_km": 10.0,
            "vis_miles": 6.0,
            "gust_mph": 11.8,
            "gust_kph": 19.0,
            "uv": 1.3
          },
          {
            "time_epoch": 1760527800,
            "time": "2025-10-15 17:00",
            "temp_c": 24.3,
            "temp_f": 75.7,
            "is_day": 1,
            "condition": {
              "text": "Patchy rain nearby",
              "icon": "//cdn.weatherapi.com/weather/64x64/day/176.png",
              "code": 1063
            },
            "wind_mph": 8.3,
            "wind_kph": 13.3,
            "wind_degree": 92,
            "wind_dir": "E",
            "pressure_mb": 1007.0,
            "pressure_in": 29.73,
            "precip_mm": 0.08,
            "precip_in": 0.0,
            "snow_cm": 0.0,
            "humidity": 74,
            "cloud": 85,
            "feelslike_c": 26.0,
            "feelslike_f": 78.9,
            "windchill_c": 24.3,
            "windchill_f": 75.7,
            "heatindex_c": 26.0,
            "heatindex_f": 78.9,
            "dewpoint_c": 19.3,
            "dewpoint_f": 66.8,
            "will_it_rain": 1,
            "chance_of_rain": 100,
            "will_it_snow": 0,
            "chance_of_snow": 0,
            "vis_km": 10.0,
            "vis_miles": 6.0,
            "gust_mph": 12.4,
            "gust_kph": 20.0,
            "uv": 0.1
          },
          {
            "time_epoch": 1760531400,
            "time": "2025-10-15 18:00",
            "temp_c": 23.1,
            "temp_f": 73.6,
            "is_day": 0,
            "condition": {
              "text": "Patchy rain nearby",
              "icon": "//cdn.weatherapi.com/weather/64x64/night/176.png",
              "code": 1063
            },
            "wind_mph": 8.1,
            "wind_kph": 13.0,
            "wind_degree": 94,
            "wind_dir": "E",
            "pressure_mb": 1008.0,
            "pressure_in": 29.76,
            "precip_mm": 0.02,
            "precip_in": 0.0,
            "snow_cm": 0.0,
            "humidity": 77,
            "cloud": 85,
            "feelslike_c": 25.1,
            "feelslike_f": 77.2,
            "windchill_c": 23.1,
            "windchill_f": 73.6,
            "heatindex_c": 25.1,
            "heatindex_f": 77.2,
            "dewpoint_c": 18.9,
            "dewpoint_f": 66.1,
            "will_it_rain": 0,
            "chance_of_rain": 63,
            "will_it_snow": 0,
            "chance_of_snow": 0,
            "vis_km": 10.0,
            "vis_miles": 6.0,
            "gust_mph": 13.1,
            "gust_kph": 21.0,
            "uv": 0
          },
          {
            "time_epoch": 1760535000,
            "time": "2025-10-15 19:00",
            "temp_c": 22.4,
            "temp_f": 72.4,
            "is_day": 0,
            "condition": {
              "text": "Patchy rain nearby",
              "icon": "//cdn.weatherapi.com/weather/64x64/night/176.png",
              "code": 1063
            },
            "wind_mph": 8.1,
            "wind_kph": 13.0,
            "wind_degree": 93,
            "wind_dir": "E",
            "pressure_mb": 1009.0,
            "pressure_in": 29.79,
            "precip_mm": 0.01,
            "precip_in": 0.0,
            "snow_cm": 0.0,
            "humidity": 81,
            "cloud": 83,
            "feelslike_c": 24.7,
            "feelslike_f": 76.5,
            "windchill_c": 22.5,
            "windchill_f": 72.4,
            "heatindex_c": 24.7,
            "heatindex_f": 76.5,
            "dewpoint_c": 19.1,
            "dewpoint_f": 66.3,
            "will_it_rain": 1,
            "chance_of_rain": 79,
            "will_it_snow": 0,
            "chance_of_snow": 0,
            "vis_km": 10.0,
            "vis_miles": 6.0,
            "gust_mph": 13.2,
            "gust_kph": 21.2,
            "uv": 0
          },
          {
            "time_epoch": 1760538600,
            "time": "2025-10-15 20:00",
            "temp_c": 22.0,
            "temp_f": 71.7,
            "is_day": 0,
            "condition": {
              "text": "Partly Cloudy ",
              "icon": "//cdn.weatherapi.com/weather/64x64/night/116.png",
              "code": 1003
            },
            "wind_mph": 8.1,
            "wind_kph": 13.0,
            "wind_degree": 92,
            "wind_dir": "E",
            "pressure_mb": 1010.0,
            "pressure_in": 29.82,
            "precip_mm": 0.0,
            "precip_in": 0.0,
            "snow_cm": 0.0,
            "humidity": 84,
            "cloud": 25,
            "feelslike_c": 24.5,
            "feelslike_f": 76.2,
            "windchill_c": 22.1,
            "windchill_f": 71.7,
            "heatindex_c": 24.5,
            "heatindex_f": 76.2,
            "dewpoint_c": 19.1,
            "dewpoint_f": 66.4,
            "will_it_rain": 0,
            "chance_of_rain": 0,
            "will_it_snow": 0,
            "chance_of_snow": 0,
            "vis_km": 10.0,
            "vis_miles": 6.0,
            "gust_mph": 13.1,
            "gust_kph": 21.1,
            "uv": 0
          },
          {
            "time_epoch": 1760542200,
            "time": "2025-10-15 21:00",
            "temp_c": 21.8,
            "temp_f": 71.2,
            "is_day": 0,
            "condition": {
              "text": "Partly Cloudy ",
              "icon": "//cdn.weatherapi.com/weather/64x64/night/116.png",
              "code": 1003
            },
            "wind_mph": 7.8,
            "wind_kph": 12.6,
            "wind_degree": 91,
            "wind_dir": "E",
            "pressure_mb": 1010.0,
            "pressure_in": 29.83,
            "precip_mm": 0.0,
            "precip_in": 0.0,
            "snow_cm": 0.0,
            "humidity": 85,
            "cloud": 33,
            "feelslike_c": 21.8,
            "feelslike_f": 71.2,
            "windchill_c": 21.8,
            "windchill_f": 71.2,
            "heatindex_c": 24.4,
            "heatindex_f": 75.9,
            "dewpoint_c": 19.2,
            "dewpoint_f": 66.5,
            "will_it_rain": 0,
            "chance_of_rain": 0,
            "will_it_snow": 0,
            "chance_of_snow": 0,
            "vis_km": 10.0,
            "vis_miles": 6.0,
            "gust_mph": 12.5,
            "gust_kph": 20.1,
            "uv": 0
          },
          {
            "time_epoch": 1760545800,
            "time": "2025-10-15 22:00",
            "temp_c": 21.4,
            "temp_f": 70.6,
            "is_day": 0,
            "condition": {
              "text": "Patchy rain nearby",
              "icon": "//cdn.weatherapi.com/weather/64x64/night/176.png",
              "code": 1063
            },
            "wind_mph": 7.6,
            "wind_kph": 12.2,
            "wind_degree": 92,
            "wind_dir": "E",
            "pressure_mb": 1010.0,
            "pressure_in": 29.82,
            "precip_mm": 0.01,
            "precip_in": 0.0,
            "snow_cm": 0.0,
            "humidity": 87,
            "cloud": 87,
            "feelslike_c": 21.4,
            "feelslike_f": 70.6,
            "windchill_c": 21.4,
            "windchill_f": 70.6,
            "heatindex_c": 24.3,
            "heatindex_f": 75.7,
            "dewpoint_c": 19.1,
            "dewpoint_f": 66.4,
            "will_it_rain": 1,
            "chance_of_rain": 76,
            "will_it_snow": 0,
            "chance_of_snow": 0,
            "vis_km": 10.0,
            "vis_miles": 6.0,
            "gust_mph": 12.2,
            "gust_kph": 19.7,
            "uv": 0
          },
          {
            "time_epoch": 1760549400,
            "time": "2025-10-15 23:00",
            "temp_c": 21.1,
            "temp_f": 70.0,
            "is_day": 0,
            "condition": {
              "text": "Partly Cloudy ",
              "icon": "//cdn.weatherapi.com/weather/64x64/night/116.png",
              "code": 1003
            },
            "wind_mph": 7.4,
            "wind_kph": 11.9,
            "wind_degree": 96,
            "wind_dir": "E",
            "pressure_mb": 1010.0,
            "pressure_in": 29.82,
            "precip_mm": 0.0,
            "precip_in": 0.0,
            "snow_cm": 0.0,
            "humidity": 89,
            "cloud": 35,
            "feelslike_c": 21.1,
            "feelslike_f": 70.0,
            "windchill_c": 21.1,
            "windchill_f": 70.0,
            "heatindex_c": 24.2,
            "heatindex_f": 75.5,
            "dewpoint_c": 19.2,
            "dewpoint_f": 66.6,
            "will_it_rain": 0,
            "chance_of_rain": 0,
            "will_it_snow": 0,
            "chance_of_snow": 0,
            "vis_km": 10.0,
            "vis_miles": 6.0,
            "gust_mph": 11.7,
            "gust_kph": 18.9,
            "uv": 0
          }
        ]
      }
    ]
  }
}